{"type":"FeatureCollection","features":[{"type":"Feature","properties":{"name":"巴博庫魯山","ele":2099.6},"geometry":{"type":"Point","coordinates":[121.4797847,24.6737391]}},{"type":"Feature","properties":{"name":"龜山島山","ele":397.6},"geometry":{"type":"Point","coordinates":[121.9531906,24.8415571]}},{"type":"Feature","properties":{"name":"御恩山","ele":1236.6},"geometry":{"type":"Point","coordinates":[121.7596881,24.3762451]}},{"type":"Feature","properties":{"name":"灣坑頭山","ele":616.1},"geometry":{"type":"Point","coordinates":[121.9104242,24.9745606]}},{"type":"Feature","properties":{"name":"喀拉業山","ele":3132.5},"geometry":{"type":"Point","coordinates":[121.321218,24.4497761]}},{"type":"Feature","properties":{"name":"蘇澳山","ele":244.75},"geometry":{"type":"Point","coordinates":[121.843839,24.6013381]}},{"type":"Feature","properties":{"name":"烘爐地山","ele":1166.1},"geometry":{"type":"Point","coordinates":[121.696411,24.8345841]}},{"type":"Feature","properties":{"name":"草湳山","ele":616.7},"geometry":{"type":"Point","coordinates":[121.7189631,24.8229981]}},{"type":"Feature","properties":{"name":"蘭崁山","ele":1476.2},"geometry":{"type":"Point","coordinates":[121.7606611,24.5376021]}},{"type":"Feature","properties":{"name":"三星山","ele":2352.4},"geometry":{"type":"Point","coordinates":[121.5639521,24.50919]}},{"type":"Feature","properties":{"name":"飯包山","ele":1856.7},"geometry":{"type":"Point","coordinates":[121.6913957,24.3909662]}},{"type":"Feature","properties":{"name":"三針後山","ele":814.97},"geometry":{"type":"Point","coordinates":[121.6456498,24.7371631]}},{"type":"Feature","properties":{"name":"大湖桶山","ele":720.9},"geometry":{"type":"Point","coordinates":[121.6529549,24.6364931]}},{"type":"Feature","properties":{"name":"大元山","ele":1486.7},"geometry":{"type":"Point","coordinates":[121.6461399,24.5597781]}},{"type":"Feature","properties":{"name":"銅山","ele":1918.3},"geometry":{"type":"Point","coordinates":[121.6546418,24.5097735]}},{"type":"Feature","properties":{"name":"鹿皮山","ele":1665.6},"geometry":{"type":"Point","coordinates":[121.727784,24.4882601]}},{"type":"Feature","properties":{"name":"金巢山","ele":1723.5},"geometry":{"type":"Point","coordinates":[121.7182764,24.3682031]}},{"type":"Feature","properties":{"name":"九分山","ele":1086.4},"geometry":{"type":"Point","coordinates":[121.571785,24.6075501]}},{"type":"Feature","properties":{"name":"烏山","ele":1624},"geometry":{"type":"Point","coordinates":[121.458151,24.6077461]}},{"type":"Feature","properties":{"name":"見晴山","ele":2490.9},"geometry":{"type":"Point","coordinates":[121.478015,24.455635]}},{"type":"Feature","properties":{"name":"石楠花山","ele":2047.1},"geometry":{"type":"Point","coordinates":[121.592535,24.3525191]}},{"type":"Feature","properties":{"name":"崙埤仔山","ele":771.76},"geometry":{"type":"Point","coordinates":[121.595372,24.7016463]}},{"type":"Feature","properties":{"name":"大湖山","ele":435.5},"geometry":{"type":"Point","coordinates":[121.6871001,24.7700471]}},{"type":"Feature","properties":{"name":"雅音山","ele":1680.3},"geometry":{"type":"Point","coordinates":[121.6410467,24.4834501]}},{"type":"Feature","properties":{"name":"源頭山","ele":1012.6},"geometry":{"type":"Point","coordinates":[121.810486,24.4915901]}},{"type":"Feature","properties":{"name":"新寮山","ele":982.5},"geometry":{"type":"Point","coordinates":[121.7514384,24.5886011]}},{"type":"Feature","properties":{"name":"大白山","ele":1368.62},"geometry":{"type":"Point","coordinates":[121.7832274,24.544749]}},{"type":"Feature","properties":{"name":"盆盆山","ele":1019},"geometry":{"type":"Point","coordinates":[121.521419,24.6381411]}},{"type":"Feature","properties":{"name":"龜山","ele":182},"geometry":{"type":"Point","coordinates":[121.8173205,24.4559333]}},{"type":"Feature","properties":{"name":"清水山","ele":766},"geometry":{"type":"Point","coordinates":[121.6168851,24.6120811]}},{"type":"Feature","properties":{"name":"遭難山","ele":1912.4},"geometry":{"type":"Point","coordinates":[121.604814,24.5476921]}},{"type":"Feature","properties":{"name":"來藝婦山","ele":775.4},"geometry":{"type":"Point","coordinates":[121.6574628,24.6040861]}},{"type":"Feature","properties":{"name":"小南澳山","ele":727.5},"geometry":{"type":"Point","coordinates":[121.705178,24.5959661]}},{"type":"Feature","properties":{"name":"濁水山","ele":936},"geometry":{"type":"Point","coordinates":[121.7554231,24.3455063]}},{"type":"Feature","properties":{"name":"大南澳嶺","ele":1167.4},"geometry":{"type":"Point","coordinates":[121.728458,24.4424611]}},{"type":"Feature","properties":{"name":"飯包尖山","ele":1622.8},"geometry":{"type":"Point","coordinates":[121.6669346,24.4090661]}},{"type":"Feature","properties":{"name":"富太山","ele":1351.1},"geometry":{"type":"Point","coordinates":[121.6609741,24.4526083]}},{"type":"Feature","properties":{"name":"檜樹山","ele":1737.5},"geometry":{"type":"Point","coordinates":[121.5772967,24.5499551]}},{"type":"Feature","properties":{"name":"蕃社坑山","ele":1062.2},"geometry":{"type":"Point","coordinates":[121.6869059,24.5688141]}},{"type":"Feature","properties":{"name":"十字路山","ele":1106.1},"geometry":{"type":"Point","coordinates":[121.488927,24.5455751]}},{"type":"Feature","properties":{"name":"神代山","ele":1564.5},"geometry":{"type":"Point","coordinates":[121.4752901,24.5177279]}},{"type":"Feature","properties":{"name":"見睛山","ele":1879},"geometry":{"type":"Point","coordinates":[121.5240447,24.5103571]}},{"type":"Feature","properties":{"name":"加羅山","ele":2320.4},"geometry":{"type":"Point","coordinates":[121.478832,24.4807351]}},{"type":"Feature","properties":{"name":"四圍仙山","ele":1641.1},"geometry":{"type":"Point","coordinates":[121.4291949,24.5641953]}},{"type":"Feature","properties":{"name":"留茂安山","ele":1365.5},"geometry":{"type":"Point","coordinates":[121.431628,24.5372301]}},{"type":"Feature","properties":{"name":"西馬縫山","ele":1193},"geometry":{"type":"Point","coordinates":[121.5279011,24.5691991]}},{"type":"Feature","properties":{"name":"旗山","ele":1134.5},"geometry":{"type":"Point","coordinates":[121.4999931,24.6172901]}},{"type":"Feature","properties":{"name":"婆羅山","ele":1413.2},"geometry":{"type":"Point","coordinates":[121.4770971,24.639464]}},{"type":"Feature","properties":{"name":"東保津寒山","ele":1962.5},"geometry":{"type":"Point","coordinates":[121.4035099,24.5683611]}},{"type":"Feature","properties":{"name":"馬惱山","ele":2577.5},"geometry":{"type":"Point","coordinates":[121.3629101,24.492522]}},{"type":"Feature","properties":{"name":"香本山","ele":1754.2},"geometry":{"type":"Point","coordinates":[121.391414,24.4827281]}},{"type":"Feature","properties":{"name":"羅葉尾山","ele":2714.7},"geometry":{"type":"Point","coordinates":[121.326915,24.3988121]}},{"type":"Feature","properties":{"name":"邊吉岩山","ele":2823.6},"geometry":{"type":"Point","coordinates":[121.344429,24.4822841]}},{"type":"Feature","properties":{"name":"塚呂馬布山","ele":2223.4},"geometry":{"type":"Point","coordinates":[121.437874,24.4332141]}},{"type":"Feature","properties":{"name":"佐得寒山","ele":2081.1},"geometry":{"type":"Point","coordinates":[121.356413,24.4386061]}},{"type":"Feature","properties":{"name":"審馬陣山","ele":3139.9},"geometry":{"type":"Point","coordinates":[121.417492,24.3801643]}},{"type":"Feature","properties":{"name":"多加屯山","ele":2793.4},"geometry":{"type":"Point","coordinates":[121.3811518,24.3677387]}},{"type":"Feature","properties":{"name":"多門山","ele":2272.1},"geometry":{"type":"Point","coordinates":[121.5195211,24.4824641]}},{"type":"Feature","properties":{"name":"南湖北山","ele":3534.2},"geometry":{"type":"Point","coordinates":[121.4372559,24.3836701]}},{"type":"Feature","properties":{"name":"府塔山","ele":2857},"geometry":{"type":"Point","coordinates":[121.4596319,24.4147411]}},{"type":"Feature","properties":{"name":"檜山","ele":2020.84},"geometry":{"type":"Point","coordinates":[121.5507373,24.4571483]}},{"type":"Feature","properties":{"name":"敷島山","ele":2003.2},"geometry":{"type":"Point","coordinates":[121.524348,24.389113]}},{"type":"Feature","properties":{"name":"霧覽山","ele":2472.8},"geometry":{"type":"Point","coordinates":[121.472528,24.4345171]}},{"type":"Feature","properties":{"name":"芳北山","ele":1127.7},"geometry":{"type":"Point","coordinates":[121.5588891,24.3923431]}},{"type":"Feature","properties":{"name":"馬望峰","ele":1247.3},"geometry":{"type":"Point","coordinates":[121.5968901,24.3882241]}},{"type":"Feature","properties":{"name":"束穗山","ele":2764.2},"geometry":{"type":"Point","coordinates":[121.4862629,24.378585]}},{"type":"Feature","properties":{"name":"清花山","ele":1982.7},"geometry":{"type":"Point","coordinates":[121.5713379,24.358164]}},{"type":"Feature","properties":{"name":"巴奈良山","ele":2367.5},"geometry":{"type":"Point","coordinates":[121.519907,24.3717521]}},{"type":"Feature","properties":{"name":"銘山","ele":1848.7},"geometry":{"type":"Point","coordinates":[121.5958121,24.4600581]}},{"type":"Feature","properties":{"name":"麻加蘭山","ele":1237},"geometry":{"type":"Point","coordinates":[121.621331,24.3793811]}},{"type":"Feature","properties":{"name":"俚與邊山","ele":1138.1},"geometry":{"type":"Point","coordinates":[121.6283601,24.4464011]}},{"type":"Feature","properties":{"name":"南澳嶺北峰","ele":722.7},"geometry":{"type":"Point","coordinates":[121.832036,24.4812821]}},{"type":"Feature","properties":{"name":"多加屯山前峰","ele":2722.5},"geometry":{"type":"Point","coordinates":[121.375167,24.3692633]}},{"type":"Feature","properties":{"name":"虎背山","ele":801.8},"geometry":{"type":"Point","coordinates":[121.6791489,24.8026671]}},{"type":"Feature","properties":{"name":"牛鬥山","ele":416.2},"geometry":{"type":"Point","coordinates":[121.5936216,24.638386]}},{"type":"Feature","properties":{"name":"清水湖山","ele":347},"geometry":{"type":"Point","coordinates":[121.60314,24.6521781]}},{"type":"Feature","properties":{"name":"野分山","ele":327},"geometry":{"type":"Point","coordinates":[121.715611,24.6249661]}},{"type":"Feature","properties":{"name":"大湖山","ele":312.55},"geometry":{"type":"Point","coordinates":[121.7157265,24.6473897]}},{"type":"Feature","properties":{"name":"米羅山","ele":1737.5},"geometry":{"type":"Point","coordinates":[121.374396,24.453499]}},{"type":"Feature","properties":{"name":"鵲子山","ele":679.2},"geometry":{"type":"Point","coordinates":[121.76733,24.850237]}},{"type":"Feature","properties":{"name":"九股山","ele":166.9},"geometry":{"type":"Point","coordinates":[121.8221573,24.6097859]}},{"type":"Feature","properties":{"name":"鹽草林山","ele":395},"geometry":{"type":"Point","coordinates":[121.801878,24.8716222]}},{"type":"Feature","properties":{"name":"溪邊頂山","ele":736.4},"geometry":{"type":"Point","coordinates":[121.8595097,24.9333813]}},{"type":"Feature","properties":{"name":"員山","ele":64.3},"geometry":{"type":"Point","coordinates":[121.760939,24.6407361]}},{"type":"Feature","properties":{"name":"火燒寮山","ele":310.43},"geometry":{"type":"Point","coordinates":[121.8348182,24.8869054]}},{"type":"Feature","properties":{"name":"蕃薯寮山","ele":454.65},"geometry":{"type":"Point","coordinates":[121.8932552,24.9548321]}},{"type":"Feature","properties":{"name":"三方向山","ele":615.4},"geometry":{"type":"Point","coordinates":[121.861356,24.9635131]}},{"type":"Feature","properties":{"name":"鶯子嶺","ele":941.6},"geometry":{"type":"Point","coordinates":[121.8118439,24.9064198]}},{"type":"Feature","properties":{"name":"米曲瑤山","ele":225.4},"geometry":{"type":"Point","coordinates":[121.7442203,24.8049175]}},{"type":"Feature","properties":{"name":"望洋山","ele":2048},"geometry":{"type":"Point","coordinates":[121.6163011,24.5106282]}},{"type":"Feature","properties":{"name":"大金面山","ele":417.1},"geometry":{"type":"Point","coordinates":[121.7891015,24.8576448]}},{"type":"Feature","properties":{"name":"風空子溪山","ele":908.2},"geometry":{"type":"Point","coordinates":[121.7841259,24.8901191]}},{"type":"Feature","properties":{"name":"九股山","ele":642.4},"geometry":{"type":"Point","coordinates":[121.79566,24.8831171]}},{"type":"Feature","properties":{"name":"岩藏山","ele":185.58},"geometry":{"type":"Point","coordinates":[121.8513853,24.8967371]}},{"type":"Feature","properties":{"name":"石坑山","ele":515.7},"geometry":{"type":"Point","coordinates":[121.834462,24.9034302]}},{"type":"Feature","properties":{"name":"叢雲山","ele":711.5},"geometry":{"type":"Point","coordinates":[121.851939,24.9236119]}},{"type":"Feature","properties":{"name":"鹿窟尾山","ele":550.7},"geometry":{"type":"Point","coordinates":[121.882911,24.9641162]}},{"type":"Feature","properties":{"name":"鷹石尖","ele":412.44},"geometry":{"type":"Point","coordinates":[121.8833186,24.9412115]}},{"type":"Feature","properties":{"name":"福隆山","ele":472.8},"geometry":{"type":"Point","coordinates":[121.9458825,24.9876449]}},{"type":"Feature","properties":{"name":"梗枋山","ele":140},"geometry":{"type":"Point","coordinates":[121.870035,24.9080957]}},{"type":"Feature","properties":{"name":"橋板湖山","ele":302.82},"geometry":{"type":"Point","coordinates":[121.8756174,24.9202429]}},{"type":"Feature","properties":{"name":"大里簡山","ele":161.98},"geometry":{"type":"Point","coordinates":[121.912888,24.9550731]}},{"type":"Feature","properties":{"name":"龜山頭山","ele":232},"geometry":{"type":"Point","coordinates":[121.962752,24.8371251]}},{"type":"Feature","properties":{"name":"石硿山","ele":196.36},"geometry":{"type":"Point","coordinates":[121.8596468,24.5841336]}},{"type":"Feature","properties":{"name":"大埤山","ele":51.3},"geometry":{"type":"Point","coordinates":[121.790952,24.6201191]}},{"type":"Feature","properties":{"name":"礁溪山","ele":270.3},"geometry":{"type":"Point","coordinates":[121.7616871,24.8308911]}},{"type":"Feature","properties":{"name":"匏崙山","ele":366.3},"geometry":{"type":"Point","coordinates":[121.714115,24.7940781]}},{"type":"Feature","properties":{"name":"莿子崙山","ele":61.8},"geometry":{"type":"Point","coordinates":[121.732723,24.7895681]}},{"type":"Feature","properties":{"name":"鎮頭山","ele":300.8},"geometry":{"type":"Point","coordinates":[121.70557,24.7654292]}},{"type":"Feature","properties":{"name":"大湖庄山","ele":222.92},"geometry":{"type":"Point","coordinates":[121.688934,24.7334821]}},{"type":"Feature","properties":{"name":"南興山","ele":286.3},"geometry":{"type":"Point","coordinates":[121.773178,24.6157491]}},{"type":"Feature","properties":{"name":"崩山湖山","ele":300},"geometry":{"type":"Point","coordinates":[121.669966,24.7619098]}},{"type":"Feature","properties":{"name":"貢仔子湖山","ele":390},"geometry":{"type":"Point","coordinates":[121.6729045,24.7346847]}},{"type":"Feature","properties":{"name":"野分山東峰","ele":302},"geometry":{"type":"Point","coordinates":[121.7200644,24.624946]}},{"type":"Feature","properties":{"name":"蚊子坑山","ele":125.1},"geometry":{"type":"Point","coordinates":[121.708585,24.6526661]}},{"type":"Feature","properties":{"name":"芃芃山","ele":1710.2},"geometry":{"type":"Point","coordinates":[121.471514,24.6246081]}},{"type":"Feature","properties":{"name":"棲蘭山","ele":416.32},"geometry":{"type":"Point","coordinates":[121.5128761,24.5989504]}},{"type":"Feature","properties":{"name":"南湖大山北峰","ele":3563},"geometry":{"type":"Point","coordinates":[121.4417124,24.3740058]}},{"type":"Feature","properties":{"name":"南湖大山東北峰","ele":3557},"geometry":{"type":"Point","coordinates":[121.4467977,24.3759801]}},{"type":"Feature","properties":{"name":"南湖大山東南峰","ele":3478},"geometry":{"type":"Point","coordinates":[121.4649295,24.3558312]}},{"type":"Feature","properties":{"name":"陶塞峰","ele":3519},"geometry":{"type":"Point","coordinates":[121.4600372,24.3590926]}},{"type":"Feature","properties":{"name":"南拳頭母山基點峰","ele":677},"geometry":{"type":"Point","coordinates":[121.5777833,24.6767667]}},{"type":"Feature","properties":{"name":"松蘿山","ele":348},"geometry":{"type":"Point","coordinates":[121.5938,24.6713167]}},{"type":"Feature","properties":{"name":"四季薰山","ele":1387.6},"geometry":{"type":"Point","coordinates":[121.440748,24.4870841]}},{"type":"Feature","properties":{"name":"東阿玉山","ele":1007},"geometry":{"type":"Point","coordinates":[121.6317939,24.7862744]}},{"type":"Feature","properties":{"name":"烏岩角","ele":null},"geometry":{"type":"Point","coordinates":[121.8753409,24.5343773]}},{"type":"Feature","properties":{"name":"福德山","ele":542.1},"geometry":{"type":"Point","coordinates":[121.8969829,24.9668961]}},{"type":"Feature","properties":{"name":"金巢北山","ele":1631.7},"geometry":{"type":"Point","coordinates":[121.713578,24.3896171]}},{"type":"Feature","properties":{"name":"砲臺山","ele":1090.5},"geometry":{"type":"Point","coordinates":[121.638347,24.4171941]}},{"type":"Feature","properties":{"name":"1048","ele":null},"geometry":{"type":"Point","coordinates":[121.6427549,24.4188834]}},{"type":"Feature","properties":{"name":"北方澳鼻山","ele":106},"geometry":{"type":"Point","coordinates":[121.8827152,24.6004062]}},{"type":"Feature","properties":{"name":"七星嶺","ele":229},"geometry":{"type":"Point","coordinates":[121.8532409,24.6034574]}},{"type":"Feature","properties":{"name":"烏石鼻","ele":177},"geometry":{"type":"Point","coordinates":[121.8586296,24.4812235]}},{"type":"Feature","properties":{"name":"南澳嶺","ele":702.2},"geometry":{"type":"Point","coordinates":[121.8315271,24.4761882]}},{"type":"Feature","properties":{"name":"睏牛山","ele":588},"geometry":{"type":"Point","coordinates":[121.8707374,24.9591061]}},{"type":"Feature","properties":{"name":"西阿玉山","ele":null},"geometry":{"type":"Point","coordinates":[121.5921065,24.7875627]}},{"type":"Feature","properties":{"name":"北屏風山","ele":944},"geometry":{"type":"Point","coordinates":[121.7294808,24.5347575]}},{"type":"Feature","properties":{"name":"西烏帽山","ele":1007},"geometry":{"type":"Point","coordinates":[121.7147487,24.573465]}},{"type":"Feature","properties":{"name":"蛇山","ele":null},"geometry":{"type":"Point","coordinates":[121.8279986,24.5223426]}},{"type":"Feature","properties":{"name":"畚萁湖山","ele":471},"geometry":{"type":"Point","coordinates":[121.8231641,24.591008]}},{"type":"Feature","properties":{"name":"獨立山","ele":554},"geometry":{"type":"Point","coordinates":[121.4771801,24.576467]}},{"type":"Feature","properties":{"name":"大山","ele":87},"geometry":{"type":"Point","coordinates":[121.873518,24.5820973]}},{"type":"Feature","properties":{"name":"東丘斯山","ele":2176},"geometry":{"type":"Point","coordinates":[121.4031794,24.5915263]}},{"type":"Feature","properties":{"name":"東壘山","ele":null},"geometry":{"type":"Point","coordinates":[121.5319488,24.6036303]}},{"type":"Feature","properties":{"name":"秀魯葉山","ele":2784.1},"geometry":{"type":"Point","coordinates":[121.3266839,24.4200251]}},{"type":"Feature","properties":{"name":"1136峰","ele":1136},"geometry":{"type":"Point","coordinates":[121.5238328,24.6534973]}},{"type":"Feature","properties":{"name":"1327峰","ele":1327},"geometry":{"type":"Point","coordinates":[121.5267319,24.6685336]}},{"type":"Feature","properties":{"name":"南拳頭母山","ele":977},"geometry":{"type":"Point","coordinates":[121.5599715,24.6884408]}},{"type":"Feature","properties":{"name":"莫很山","ele":null},"geometry":{"type":"Point","coordinates":[121.6197011,24.4094666]}},{"type":"Feature","properties":{"name":"大和山","ele":1413.5},"geometry":{"type":"Point","coordinates":[121.590806,24.4239261]}},{"type":"Feature","properties":{"name":"鶯子頂山","ele":1001.4},"geometry":{"type":"Point","coordinates":[121.7976461,24.901012]}},{"type":"Feature","properties":{"name":"大安埤山","ele":421.5},"geometry":{"type":"Point","coordinates":[121.6689151,24.7243351]}},{"type":"Feature","properties":{"name":"石城山","ele":348.14},"geometry":{"type":"Point","coordinates":[121.9607281,24.9879261]}},{"type":"Feature","properties":{"name":"桶盤堀尖東峰","ele":437.76},"geometry":{"type":"Point","coordinates":[121.9374281,24.9829421]}},{"type":"Feature","properties":{"name":"下銅山","ele":1826.4},"geometry":{"type":"Point","coordinates":[121.68516,24.5016201]}},{"type":"Feature","properties":{"name":"拔都諾府山","ele":3166.7},"geometry":{"type":"Point","coordinates":[121.4414609,24.400605]}},{"type":"Feature","properties":{"name":"巴都服山","ele":3347},"geometry":{"type":"Point","coordinates":[121.4387728,24.3917943]}},{"type":"Feature","properties":{"name":"復興尖山","ele":1851.81},"geometry":{"type":"Point","coordinates":[121.4487948,24.6596936]}},{"type":"Feature","properties":{"name":"古魯南峰","ele":1021.8},"geometry":{"type":"Point","coordinates":[121.6594977,24.5769601]}},{"type":"Feature","properties":{"name":"古魯山","ele":976.9},"geometry":{"type":"Point","coordinates":[121.661919,24.5874461]}},{"type":"Feature","properties":{"name":"大陂丘山","ele":261.8},"geometry":{"type":"Point","coordinates":[121.7348869,24.6371971]}},{"type":"Feature","properties":{"name":"北五峰旗山","ele":695.9},"geometry":{"type":"Point","coordinates":[121.739854,24.8470681]}},{"type":"Feature","properties":{"name":"舊寮山","ele":701},"geometry":{"type":"Point","coordinates":[121.7317423,24.5995501]}},{"type":"Feature","properties":{"name":"鳳紗山","ele":987},"geometry":{"type":"Point","coordinates":[121.6974664,24.5787682]}},{"type":"Feature","properties":{"name":"寺蕃山","ele":1095},"geometry":{"type":"Point","coordinates":[121.7397809,24.5426534]}},{"type":"Feature","properties":{"name":"太和山","ele":712.5},"geometry":{"type":"Point","coordinates":[121.8255503,24.9051011]}},{"type":"Feature","properties":{"name":"枕頭山","ele":77},"geometry":{"type":"Point","coordinates":[121.7204948,24.7697892]}},{"type":"Feature","properties":{"name":"東巷山","ele":573},"geometry":{"type":"Point","coordinates":[121.5552686,24.6218948]}},{"type":"Feature","properties":{"name":"牛衝鬪山","ele":346},"geometry":{"type":"Point","coordinates":[121.564066,24.6370961]}},{"type":"Feature","properties":{"name":"長嶺路山","ele":254.6},"geometry":{"type":"Point","coordinates":[121.6189201,24.6846811]}},{"type":"Feature","properties":{"name":"西帽山","ele":961},"geometry":{"type":"Point","coordinates":[121.8145191,24.5511612]}},{"type":"Feature","properties":{"name":"西德山北峰","ele":1193.9},"geometry":{"type":"Point","coordinates":[121.7511069,24.5625881]}},{"type":"Feature","properties":{"name":"多聞山","ele":754.4},"geometry":{"type":"Point","coordinates":[121.485873,24.573714]}},{"type":"Feature","properties":{"name":"烏帽子山","ele":911.7},"geometry":{"type":"Point","coordinates":[121.48,24.5667471]}},{"type":"Feature","properties":{"name":"多望山北峰","ele":929.4},"geometry":{"type":"Point","coordinates":[121.484243,24.559886]}},{"type":"Feature","properties":{"name":"天送埤山","ele":186.6},"geometry":{"type":"Point","coordinates":[121.6183221,24.6589081]}},{"type":"Feature","properties":{"name":"八角子寮山","ele":156.3},"geometry":{"type":"Point","coordinates":[121.695866,24.6632271]}},{"type":"Feature","properties":{"name":"茅埔圍山","ele":93.35},"geometry":{"type":"Point","coordinates":[121.7366361,24.648314]}},{"type":"Feature","properties":{"name":"四季薰山西南峰","ele":1391.5},"geometry":{"type":"Point","coordinates":[121.4405508,24.4866351]}},{"type":"Feature","properties":{"name":"旗山東峰","ele":1115.6},"geometry":{"type":"Point","coordinates":[121.50107,24.6170291]}},{"type":"Feature","properties":{"name":"虎背山前峰(熊腰山)","ele":657},"geometry":{"type":"Point","coordinates":[121.6863524,24.7996793]}},{"type":"Feature","properties":{"name":"東三針後山","ele":698},"geometry":{"type":"Point","coordinates":[121.647887,24.7357974]}},{"type":"Feature","properties":{"name":"虎頭坡山","ele":137},"geometry":{"type":"Point","coordinates":[121.7461526,24.8141214]}},{"type":"Feature","properties":{"name":"雙子山東南峰","ele":662},"geometry":{"type":"Point","coordinates":[121.7092283,24.4322859]}},{"type":"Feature","properties":{"name":"西德山","ele":1230.2},"geometry":{"type":"Point","coordinates":[121.754323,24.5529721]}},{"type":"Feature","properties":{"name":"濁水山","ele":1317},"geometry":{"type":"Point","coordinates":[121.5671142,24.5826731]}},{"type":"Feature","properties":{"name":"芳山","ele":2031},"geometry":{"type":"Point","coordinates":[121.5922475,24.4863635]}},{"type":"Feature","properties":{"name":"舊寮山西北峰","ele":566},"geometry":{"type":"Point","coordinates":[121.7242941,24.6069956]}},{"type":"Feature","properties":{"name":"舊寮山北峰","ele":368},"geometry":{"type":"Point","coordinates":[121.7255524,24.6117849]}},{"type":"Feature","properties":{"name":"旗山主峰","ele":1316.1},"geometry":{"type":"Point","coordinates":[121.486636,24.6201822]}},{"type":"Feature","properties":{"name":"佐宇漢山","ele":2005.1},"geometry":{"type":"Point","coordinates":[121.513984,24.4576251]}},{"type":"Feature","properties":{"name":"山櫻山","ele":1871.6},"geometry":{"type":"Point","coordinates":[121.568473,24.4356781]}},{"type":"Feature","properties":{"name":"西馬縫山北峰","ele":1060},"geometry":{"type":"Point","coordinates":[121.5235162,24.5752261]}},{"type":"Feature","properties":{"name":"香本山東南","ele":1521.4},"geometry":{"type":"Point","coordinates":[121.3943703,24.4787937]}},{"type":"Feature","properties":{"name":"獨立山山","ele":null},"geometry":{"type":"Point","coordinates":[121.5338194,24.4607664]}},{"type":"Feature","properties":{"name":"竹仔崙山","ele":890},"geometry":{"type":"Point","coordinates":[121.7424829,24.8524487]}},{"type":"Feature","properties":{"name":"多加神山西北峰","ele":1606},"geometry":{"type":"Point","coordinates":[121.3964703,24.4315525]}},{"type":"Feature","properties":{"name":"內員山","ele":75.037},"geometry":{"type":"Point","coordinates":[121.7066444,24.7506031]}},{"type":"Feature","properties":{"name":"來藝婦山西北峰","ele":586},"geometry":{"type":"Point","coordinates":[121.648868,24.6112261]}},{"type":"Feature","properties":{"name":"大湖桶山北峰","ele":510},"geometry":{"type":"Point","coordinates":[121.658189,24.6468306]}},{"type":"Feature","properties":{"name":"九股山西北峰","ele":99.62},"geometry":{"type":"Point","coordinates":[121.8209687,24.6118762]}},{"type":"Feature","properties":{"name":"下湖山","ele":310.5},"geometry":{"type":"Point","coordinates":[121.6377297,24.6531896]}},{"type":"Feature","properties":{"name":"牛鬥山東南峰","ele":336.8},"geometry":{"type":"Point","coordinates":[121.597902,24.6362351]}},{"type":"Feature","properties":{"name":"下銅山前峰","ele":1828.5},"geometry":{"type":"Point","coordinates":[121.684382,24.5011711]}},{"type":"Feature","properties":{"name":"雙溪口山","ele":598.4},"geometry":{"type":"Point","coordinates":[121.617798,24.7516001]}},{"type":"Feature","properties":{"name":"十三分山","ele":560},"geometry":{"type":"Point","coordinates":[121.7631519,24.6076411]}},{"type":"Feature","properties":{"name":"五峰旗山","ele":720.8},"geometry":{"type":"Point","coordinates":[121.7544181,24.8466231]}},{"type":"Feature","properties":{"name":"礁水坑山","ele":629.49},"geometry":{"type":"Point","coordinates":[121.81861,24.8953342]}},{"type":"Feature","properties":{"name":"多加神山","ele":2030.859},"geometry":{"type":"Point","coordinates":[121.4059875,24.4198117]}},{"type":"Feature","properties":{"name":"魔葉名病山","ele":2976},"geometry":{"type":"Point","coordinates":[121.4320967,24.4083047]}},{"type":"Feature","properties":{"name":"外大溪山","ele":461},"geometry":{"type":"Point","coordinates":[121.871149,24.9434747]}},{"type":"Feature","properties":{"name":"斷岩山","ele":1589},"geometry":{"type":"Point","coordinates":[121.3748954,24.4102354]}},{"type":"Feature","properties":{"name":"松羅山東南峰","ele":535},"geometry":{"type":"Point","coordinates":[121.56616,24.6542809]}},{"type":"Feature","properties":{"name":"柑子頭山","ele":1256},"geometry":{"type":"Point","coordinates":[121.7509803,24.4842096]}},{"type":"Feature","properties":{"name":"多加神山北峰","ele":1681},"geometry":{"type":"Point","coordinates":[121.4075768,24.4409172]}},{"type":"Feature","properties":{"name":"塚呂馬布山西北峰","ele":1520},"geometry":{"type":"Point","coordinates":[121.4261566,24.4668837]}},{"type":"Feature","properties":{"name":"三星山西南峰","ele":2181},"geometry":{"type":"Point","coordinates":[121.5477317,24.4966425]}},{"type":"Feature","properties":{"name":"西東澳山","ele":422},"geometry":{"type":"Point","coordinates":[121.8084727,24.5300958]}},{"type":"Feature","properties":{"name":"西帽山東南峰","ele":614},"geometry":{"type":"Point","coordinates":[121.8210968,24.5363799]}},{"type":"Feature","properties":{"name":"八八峰","ele":890},"geometry":{"type":"Point","coordinates":[121.8056752,24.8987498]}},{"type":"Feature","properties":{"name":"五峰旗山東南峰","ele":552},"geometry":{"type":"Point","coordinates":[121.7590519,24.8413396]}},{"type":"Feature","properties":{"name":"紅柴林山","ele":619},"geometry":{"type":"Point","coordinates":[121.6319358,24.7153263]}},{"type":"Feature","properties":{"name":"刺竹澳山","ele":285},"geometry":{"type":"Point","coordinates":[121.6884365,24.6238643]}},{"type":"Feature","properties":{"name":"西白米甕山","ele":312},"geometry":{"type":"Point","coordinates":[121.834389,24.5835487]}},{"type":"Feature","properties":{"name":"白米甕山","ele":200},"geometry":{"type":"Point","coordinates":[121.8415641,24.5796754]}},{"type":"Feature","properties":{"name":"蕃社坑山北峰","ele":561},"geometry":{"type":"Point","coordinates":[121.6816681,24.5789204]}},{"type":"Feature","properties":{"name":"員山","ele":45},"geometry":{"type":"Point","coordinates":[121.7200748,24.7452861]}},{"type":"Feature","properties":{"name":"濁水山西峰","ele":765},"geometry":{"type":"Point","coordinates":[121.7447286,24.3475019]}},{"type":"Feature","properties":{"name":"大南澳山","ele":970},"geometry":{"type":"Point","coordinates":[121.6943824,24.5772872]}}]}